codigos/Codigos_Stewart/Codigos del dia 10-08-2024/Tamagotchi_Modos/Modo_Primitivo.v


module Modo_Primitivo #(parameter Parametro= 65)(

    // Entradas
    input clk,
    input B_reset,
    input Entrada_Sube_Nivel,
    input activo,
    // Salida
     output [0:1] Nivel 
     
);

reg [0:1] Contador_Nivel;
reg [$clog2(Parametro)-1:0] Contador_Tiempo;

initial begin
        Contador_Nivel = 3;
        Contador_Tiempo = 0;
    end


always @(posedge clk)begin

if (~B_reset) begin
    Contador_Nivel <= 3;
    Contador_Tiempo <= 0;
end else if (Contador_Tiempo == Parametro & Contador_Nivel > 0 & activo) begin
        Contador_Nivel = Contador_Nivel - 1;
        Contador_Tiempo <= 0;
end else if (~Entrada_Sube_Nivel & Contador_Nivel<3 & activo) begin
        Contador_Nivel = Contador_Nivel + 1; 
end else if (activo) begin
        Contador_Tiempo = Contador_Tiempo + 1;
end
end // Fin del Always clk

assign Nivel = Contador_Nivel;



endmodule

codigos/Modos.v
 `include "Tamagotchi_Modos/Modo_Primitivo.v"
 
 module Modos(
    //Entradas 
    input clk,
    input B_Test,
    input B_Reset,

    input B_Energia,
    input B_Medicina,
    input Entrada_Descanso,
    input Entrada_Animo,
    
    //Salidas
    output [0:1]LED_Animo,
    output [0:1]LED_Energia,
    output [0:1]LED_Descanso,
    output [0:1]LED_Medicina
);

wire [0:1] Nivel_Animo;
wire [0:1] Nivel_Energia;
wire [0:1] Nivel_Descanso;
wire [0:1] Nivel_Medicina;

reg B_MedicinaPrev;
reg B_EnergiaPrev;
reg B_Ener;
reg B_Medi;
reg flanco_ener;
reg flanco_medi;
reg activo_med;

initial begin
    B_MedicinaPrev =0 ;
    B_EnergiaPrev=0;
    B_Medi=0;
    B_Ener=0;
    flanco_ener=1;
    flanco_medi=1;
end

Modo_Primitivo #(5) Modo_Animo (.clk(clk), .Entrada_Sube_Nivel(Entrada_Animo), .Nivel(Nivel_Animo),.activo(1));
Modo_Primitivo #(5) Modo_Descanso (.clk(clk), .Entrada_Sube_Nivel(Entrada_Descanso), .Nivel(Nivel_Descanso),.activo(1));
Modo_Primitivo #(5) Modo_Energia (.clk(clk), .Entrada_Sube_Nivel(flanco_ener), .Nivel(Nivel_Energia),.activo(1));
Modo_Primitivo #(5) Modo_Medicina (.clk(clk), .Entrada_Sube_Nivel(flanco_medi), .Nivel(Nivel_Medicina),.activo(0));

always @(clk) begin
    B_MedicinaPrev=B_Medi;
    B_EnergiaPrev=B_Ener;
    B_Ener=B_Energia;
    B_Medi=B_Medicina;
    flanco_ener=(B_Ener==B_EnergiaPrev);
    flanco_medi=(B_Medi==B_MedicinaPrev);
end

assign LED_Animo = Nivel_Animo;
assign LED_Descanso = Nivel_Descanso;
assign LED_Energia = Nivel_Energia;
assign LED_Medicina = Nivel_Medicina;

endmodule

codigos/Modos_TB.v
`timescale 1ns / 1ps
`include "Tamagotchi_Modos/Modos.v"

module Modos_TB;

    reg clk;
    reg B_Test;
    reg B_Reset;

    reg B_Energia;
    reg B_Medicina;
    reg Entrada_Descanso;
    reg Entrada_Animo;
    
    //Salidas
    wire [0:1]LED_Animo;
    wire [0:1]ED_Energia;
    wire [0:1]LED_Descanso;
    wire [0:1]LED_Medicina;

 Modos uut(
    .clk(clk),
    .B_Test(B_Test),
    .B_Reset(B_Reset),

    .B_Energia(B_Energia),
    .B_Medicina(B_Medicina),
    .Entrada_Descanso(Entrada_Descanso),
    .Entrada_Animo(Entrada_Animo),
    
    //Salidas
    .LED_Animo(LED_Animo),
    .LED_Energia(LED_Energia),
    .LED_Descanso(LED_Descanso),
    .LED_Medicina(LED_Medicina)
);

    initial begin
        clk = 0;
        B_Energia=0;
        B_Medicina=0; 

        #15
        B_Medicina=1;
        B_Energia=1;
    end

    always #1 clk = ~clk; // Cambia cada nanosegundo (1ns)

    initial begin: TEST_CASE
        $dumpfile("Modos.vcd");
        $dumpvars(-1, uut);
        #(20000) $finish;
    end

endmodule

codigos/Codigos_Stewart/Codigos del dia 10-08-2024/build/Modos.vcd
$date
	Sun Jul 28 22:01:19 2024
$end
$version
	Icarus Verilog
$end
$timescale
	1ps
$end
$scope module Modos_TB $end
$scope module uut $end
$var wire 1 ! B_Energia $end
$var wire 1 " B_Medicina $end
$var wire 1 # B_Reset $end
$var wire 1 $ B_Test $end
$var wire 1 % Entrada_Animo $end
$var wire 1 & Entrada_Descanso $end
$var wire 2 ' LED_Animo [0:1] $end
$var wire 2 ( LED_Descanso [0:1] $end
$var wire 2 ) LED_Energia [0:1] $end
$var wire 2 * LED_Medicina [0:1] $end
$var wire 1 + clk $end
$var wire 2 , Nivel_Medicina [0:1] $end
$var wire 2 - Nivel_Energia [0:1] $end
$var wire 2 . Nivel_Descanso [0:1] $end
$var wire 2 / Nivel_Animo [0:1] $end
$var reg 1 0 B_Ener $end
$var reg 1 1 B_EnergiaPrev $end
$var reg 1 2 B_Medi $end
$var reg 1 3 B_MedicinaPrev $end
$var reg 1 4 flanco_ener $end
$var reg 1 5 flanco_medi $end
$scope module Modo_Animo $end
$var wire 1 6 B_reset $end
$var wire 1 % Entrada_Sube_Nivel $end
$var wire 2 7 Nivel [0:1] $end
$var wire 1 8 activo $end
$var wire 1 + clk $end
$var parameter 32 9 Parametro $end
$var reg 2 : Contador_Nivel [0:1] $end
$var reg 3 ; Contador_Tiempo [2:0] $end
$upscope $end
$scope module Modo_Descanso $end
$var wire 1 < B_reset $end
$var wire 1 & Entrada_Sube_Nivel $end
$var wire 2 = Nivel [0:1] $end
$var wire 1 > activo $end
$var wire 1 + clk $end
$var parameter 32 ? Parametro $end
$var reg 2 @ Contador_Nivel [0:1] $end
$var reg 3 A Contador_Tiempo [2:0] $end
$upscope $end
$scope module Modo_Energia $end
$var wire 1 B B_reset $end
$var wire 1 4 Entrada_Sube_Nivel $end
$var wire 2 C Nivel [0:1] $end
$var wire 1 D activo $end
$var wire 1 + clk $end
$var parameter 32 E Parametro $end
$var reg 2 F Contador_Nivel [0:1] $end
$var reg 3 G Contador_Tiempo [2:0] $end
$upscope $end
$scope module Modo_Medicina $end
$var wire 1 H B_reset $end
$var wire 1 5 Entrada_Sube_Nivel $end
$var wire 2 I Nivel [0:1] $end
$var wire 1 J activo $end
$var wire 1 + clk $end
$var parameter 32 K Parametro $end
$var reg 2 L Contador_Nivel [0:1] $end
$var reg 3 M Contador_Tiempo [2:0] $end
$upscope $end
$upscope $end
$upscope $end
$enddefinitions $end
$comment Show the parameter values. $end
$dumpall
b101 K
b101 E
b101 ?
b101 9
$end
#0
$dumpvars
b0 M
b11 L
0J
b11 I
zH
b0 G
b11 F
1D
b11 C
zB
b0 A
b11 @
1>
b11 =
z<
b0 ;
b11 :
18
b11 7
z6
15
14
03
02
01
00
b11 /
b11 .
b11 -
b11 ,
0+
b11 *
b11 )
b11 (
b11 '
x&
x%
x$
x#
0"
0!
$end
#1000
b1 ;
b1 A
b1 G
1+
#2000
0+
#3000
b10 G
b10 A
b10 ;
1+
#4000
0+
#5000
b11 ;
b11 A
b11 G
1+
#6000
0+
#7000
b100 G
b100 A
b100 ;
1+
#8000
0+
#9000
b101 ;
b101 A
b101 G
1+
#10000
0+
#11000
b0 G
b0 A
b0 ;
b10 )
b10 -
b10 C
b10 F
b10 (
b10 .
b10 =
b10 @
b10 '
b10 /
b10 7
b10 :
1+
#12000
0+
#13000
b1 ;
b1 A
b1 G
1+
#14000
0+
#15000
b11 )
b11 -
b11 C
b11 F
b10 A
b10 ;
05
04
12
10
1+
1!
1"
#16000
15
14
11
13
0+
#17000
b11 ;
b11 A
b10 G
1+
#18000
0+
#19000
b11 G
b100 A
b100 ;
1+
#20000
0+
#21000
b101 ;
b101 A
b100 G
1+
#22000
0+
#23000
b0 A
b0 ;
b101 G
b1 (
b1 .
b1 =
b1 @
b1 '
b1 /
b1 7
b1 :
1+
#24000
0+
#25000
b0 G
b1 ;
b1 A
b10 )
b10 -
b10 C
b10 F
1+
#26000
0+
#27000
b1 G
b10 A
b10 ;
1+
#28000
0+
#29000
b11 ;
b11 A
b10 G
1+
#30000
0+
#31000
b11 G
b100 A
b100 ;
1+
#32000
0+
#33000
b101 ;
b101 A
b100 G
1+
#34000
0+
#35000
b0 A
b0 ;
b101 G
b0 (
b0 .
b0 =
b0 @
b0 '
b0 /
b0 7
b0 :
1+
#36000
0+
#37000
b0 G
b1 ;
b1 A
b1 )
b1 -
b1 C
b1 F
1+
#38000
0+
#39000
b1 G
b10 A
b10 ;
1+
#40000
0+
#41000
b11 ;
b11 A
b10 G
1+
#42000
0+
#43000
b11 G
b100 A
b100 ;
1+
#44000
0+
#45000
b101 ;
b101 A
b100 G
1+
#46000
0+
#47000
b101 G
b110 A
b110 ;
1+
#48000
0+
#49000
b0 G
b111 ;
b111 A
b0 )
b0 -
b0 C
b0 F
1+
#50000
0+
#51000
b1 G
b0 A
b0 ;
1+
#52000
0+
#53000
b1 ;
b1 A
b10 G
1+
#54000
0+
#55000
b11 G
b10 A
b10 ;
1+
#56000
0+
#57000
b11 ;
b11 A
b100 G
1+
#58000
0+
#59000
b101 G
b100 A
b100 ;
1+
#60000
0+
#61000
b101 ;
b101 A
b110 G
1+
#62000
0+
#63000
b111 G
b110 A
b110 ;
1+
#64000
0+
#65000
b111 ;
b111 A
b0 G
1+
#66000
0+
#67000
b1 G
b0 A
b0 ;
1+
#68000
0+
#69000
b1 ;
b1 A
b10 G
1+
#70000
0+
#71000
b11 G
b10 A
b10 ;
1+
#72000
0+
#73000
b11 ;
b11 A
b100 G
1+
#74000
0+
#75000
b101 G
b100 A
b100 ;
1+
#76000
0+
#77000
b101 ;
b101 A
b110 G
1+
#78000
0+
#79000
b111 G
b110 A
b110 ;
1+
#80000
0+
#81000
b111 ;
b111 A
b0 G
1+
#82000
0+
#83000
b1 G
b0 A
b0 ;
1+
#84000
0+
#85000
b1 ;
b1 A
b10 G
1+
#86000
0+
#87000
b11 G
b10 A
b10 ;
1+
#88000
0+
#89000
b11 ;
b11 A
b100 G
1+
#90000
0+
#91000
b101 G
b100 A
b100 ;
1+
#92000
0+
#93000
b101 ;
b101 A
b110 G
1+
#94000
0+
#95000
b111 G
b110 A
b110 ;
1+
#96000
0+
#97000
b111 ;
b111 A
b0 G
1+
#98000
0+
#99000
b1 G
b0 A
b0 ;
1+
#100000
0+
#101000
b1 ;
b1 A
b10 G
1+
#102000
0+
#103000
b11 G
b10 A
b10 ;
1+
#104000
0+
#105000
b11 ;
b11 A
b100 G
1+
#106000
0+
#107000
b101 G
b100 A
b100 ;
1+
#108000
0+
#109000
b101 ;
b101 A
b110 G
1+
#110000
0+
#111000
b111 G
b110 A
b110 ;
1+
#112000
0+
#113000
b111 ;
b111 A
b0 G
1+
#114000
0+
#115000
b1 G
b0 A
b0 ;
1+
#116000
0+
#117000
b1 ;
b1 A
b10 G
1+
#118000
0+
#119000
b11 G
b10 A
b10 ;
1+
#120000
0+
#121000
b11 ;
b11 A
b100 G
1+
#122000
0+
#123000
b101 G
b100 A
b100 ;
1+
#124000
0+
#125000
b101 ;
b101 A
b110 G
1+
#126000
0+
#127000
b111 G
b110 A
b110 ;
1+
#128000
0+
#129000
b111 ;
b111 A
b0 G
1+
#130000
0+
#131000
b1 G
b0 A
b0 ;
1+
#132000
0+
#133000
b1 ;
b1 A
b10 G
1+
#134000
0+
#135000
b11 G
b10 A
b10 ;
1+
#136000
0+
#137000
b11 ;
b11 A
b100 G
1+
#138000
0+
#139000
b101 G
b100 A
b100 ;
1+
#140000
0+
#141000
b101 ;
b101 A
b110 G
1+
#142000
0+
#143000
b111 G
b110 A
b110 ;
1+
#144000
0+
#145000
b111 ;
b111 A
b0 G
1+
#146000
0+
#147000
b1 G
b0 A
b0 ;
1+
#148000
0+
#149000
b1 ;
b1 A
b10 G
1+
#150000
0+
#151000
b11 G
b10 A
b10 ;
1+
#152000
0+
#153000
b11 ;
b11 A
b100 G
1+
#154000
0+
#155000
b101 G
b100 A
b100 ;
1+
#156000
0+
#157000
b101 ;
b101 A
b110 G
1+
#158000
0+
#159000
b111 G
b110 A
b110 ;
1+
#160000
0+
#161000
b111 ;
b111 A
b0 G
1+
#162000
0+
#163000
b1 G
b0 A
b0 ;
1+
#164000
0+
#165000
b1 ;
b1 A
b10 G
1+
#166000
0+
#167000
b11 G
b10 A
b10 ;
1+
#168000
0+
#169000
b11 ;
b11 A
b100 G
1+
#170000
0+
#171000
b101 G
b100 A
b100 ;
1+
#172000
0+
#173000
b101 ;
b101 A
b110 G
1+
#174000
0+
#175000
b111 G
b110 A
b110 ;
1+
#176000
0+
#177000
b111 ;
b111 A
b0 G
1+
#178000
0+
#179000
b1 G
b0 A
b0 ;
1+
#180000
0+
#181000
b1 ;
b1 A
b10 G
1+
#182000
0+
#183000
b11 G
b10 A
b10 ;
1+
#184000
0+
#185000
b11 ;
b11 A
b100 G
1+
#186000
0+
#187000
b101 G
b100 A
b100 ;
1+
#188000
0+
#189000
b101 ;
b101 A
b110 G
1+
#190000
0+
#191000
b111 G
b110 A
b110 ;
1+
#192000
0+
#193000
b111 ;
b111 A
b0 G
1+
#194000
0+
#195000
b1 G
b0 A
b0 ;
1+
#196000
0+
#197000
b1 ;
b1 A
b10 G
1+
#198000
0+
#199000
b11 G
b10 A
b10 ;
1+
#200000
0+
#201000
b11 ;
b11 A
b100 G
1+
#202000
0+
#203000
b101 G
b100 A
b100 ;
1+
#204000
0+
#205000
b101 ;
b101 A
b110 G
1+
#206000
0+
#207000
b111 G
b110 A
b110 ;
1+
#208000
0+
#209000
b111 ;
b111 A
b0 G
1+
#210000
0+
#211000
b1 G
b0 A
b0 ;
1+
#212000
0+
#213000
b1 ;
b1 A
b10 G
1+
#214000
0+
#215000
b11 G
b10 A
b10 ;
1+
#216000
0+
#217000
b11 ;
b11 A
b100 G
1+
#218000
0+
#219000
b101 G
b100 A
b100 ;
1+
#220000
0+
#221000
b101 ;
b101 A
b110 G
1+
#222000
0+
#223000
b111 G
b110 A
b110 ;
1+
#224000
0+
#225000
b111 ;
b111 A
b0 G
1+
#226000
0+
#227000
b1 G
b0 A
b0 ;
1+
#228000
0+
#229000
b1 ;
b1 A
b10 G
1+
#230000
0+
#231000
b11 G
b10 A
b10 ;
1+
#232000
0+
#233000
b11 ;
b11 A
b100 G
1+
#234000
0+
#235000
b101 G
b100 A
b100 ;
1+
#236000
0+
#237000
b101 ;
b101 A
b110 G
1+
#238000
0+
#239000
b111 G
b110 A
b110 ;
1+
#240000
0+
#241000
b111 ;
b111 A
b0 G
1+
#242000
0+
#243000
b1 G
b0 A
b0 ;
1+
#244000
0+
#245000
b1 ;
b1 A
b10 G
1+
#246000
0+
#247000
b11 G
b10 A
b10 ;
1+
#248000
0+
#249000
b11 ;
b11 A
b100 G
1+
#250000
0+
#251000
b101 G
b100 A
b100 ;
1+
#252000
0+
#253000
b101 ;
b101 A
b110 G
1+
#254000
0+
#255000
b111 G
b110 A
b110 ;
1+
#256000
0+
#257000
b111 ;
b111 A
b0 G
1+
#258000
0+
#259000
b1 G
b0 A
b0 ;
1+
#260000
0+
#261000
b1 ;
b1 A
b10 G
1+
#262000
0+
#263000
b11 G
b10 A
b10 ;
1+
#264000
0+
#265000
b11 ;
b11 A
b100 G
1+
#266000
0+
#267000
b101 G
b100 A
b100 ;
1+
#268000
0+
#269000
b101 ;
b101 A
b110 G
1+
#270000
0+
#271000
b111 G
b110 A
b110 ;
1+
#272000
0+
#273000
b111 ;
b111 A
b0 G
1+
#274000
0+
#275000
b1 G
b0 A
b0 ;
1+
#276000
0+
#277000
b1 ;
b1 A
b10 G
1+
#278000
0+
#279000
b11 G
b10 A
b10 ;
1+
#280000
0+
#281000
b11 ;
b11 A
b100 G
1+
#282000
0+
#283000
b101 G
b100 A
b100 ;
1+
#284000
0+
#285000
b101 ;
b101 A
b110 G
1+
#286000
0+
#287000
b111 G
b110 A
b110 ;
1+
#288000
0+
#289000
b111 ;
b111 A
b0 G
1+
#290000
0+
#291000
b1 G
b0 A
b0 ;
1+
#292000
0+
#293000
b1 ;
b1 A
b10 G
1+
#294000
0+
#295000
b11 G
b10 A
b10 ;
1+
#296000
0+
#297000
b11 ;
b11 A
b100 G
1+
#298000
0+
#299000
b101 G
b100 A
b100 ;
1+
#300000
0+
#301000
b101 ;
b101 A
b110 G
1+
#302000
0+
#303000
b111 G
b110 A
b110 ;
1+
#304000
0+
#305000
b111 ;
b111 A
b0 G
1+
#306000
0+
#307000
b1 G
b0 A
b0 ;
1+
#308000
0+
#309000
b1 ;
b1 A
b10 G
1+
#310000
0+
#311000
b11 G
b10 A
b10 ;
1+
#312000
0+
#313000
b11 ;
b11 A
b100 G
1+
#314000
0+
#315000
b101 G
b100 A
b100 ;
1+
#316000
0+
#317000
b101 ;
b101 A
b110 G
1+
#318000
0+
#319000
b111 G
b110 A
b110 ;
1+
#320000
0+
#321000
b111 ;
b111 A
b0 G
1+
#322000
0+
#323000
b1 G
b0 A
b0 ;
1+
#324000
0+
#325000
b1 ;
b1 A
b10 G
1+
#326000
0+
#327000
b11 G
b10 A
b10 ;
1+
#328000
0+
#329000
b11 ;
b11 A
b100 G
1+
#330000
0+
#331000
b101 G
b100 A
b100 ;
1+
#332000
0+
#333000
b101 ;
b101 A
b110 G
1+
#334000
0+
#335000
b111 G
b110 A
b110 ;
1+
#336000
0+
#337000
b111 ;
b111 A
b0 G
1+
#338000
0+
#339000
b1 G
b0 A
b0 ;
1+
#340000
0+
#341000
b1 ;
b1 A
b10 G
1+
#342000
0+
#343000
b11 G
b10 A
b10 ;
1+
#344000
0+
#345000
b11 ;
b11 A
b100 G
1+
#346000
0+
#347000
b101 G
b100 A
b100 ;
1+
#348000
0+
#349000
b101 ;
b101 A
b110 G
1+
#350000
0+
#351000
b111 G
b110 A
b110 ;
1+
#352000
0+
#353000
b111 ;
b111 A
b0 G
1+
#354000
0+
#355000
b1 G
b0 A
b0 ;
1+
#356000
0+
#357000
b1 ;
b1 A
b10 G
1+
#358000
0+
#359000
b11 G
b10 A
b10 ;
1+
#360000
0+
#361000
b11 ;
b11 A
b100 G
1+
#362000
0+
#363000
b101 G
b100 A
b100 ;
1+
#364000
0+
#365000
b101 ;
b101 A
b110 G
1+
#366000
0+
#367000
b111 G
b110 A
b110 ;
1+
#368000
0+
#369000
b111 ;
b111 A
b0 G
1+
#370000
0+
#371000
b1 G
b0 A
b0 ;
1+
#372000
0+
#373000
b1 ;
b1 A
b10 G
1+
#374000
0+
#375000
b11 G
b10 A
b10 ;
1+
#376000
0+
#377000
b11 ;
b11 A
b100 G
1+
#378000
0+
#379000
b101 G
b100 A
b100 ;
1+
#380000
0+
#381000
b101 ;
b101 A
b110 G
1+
#382000
0+
#383000
b111 G
b110 A
b110 ;
1+
#384000
0+
#385000
b111 ;
b111 A
b0 G
1+
#386000
0+
#387000
b1 G
b0 A
b0 ;
1+
#388000
0+
#389000
b1 ;
b1 A
b10 G
1+
#390000
0+
#391000
b11 G
b10 A
b10 ;
1+
#392000
0+
#393000
b11 ;
b11 A
b100 G
1+
#394000
0+
#395000
b101 G
b100 A
b100 ;
1+
#396000
0+
#397000
b101 ;
b101 A
b110 G
1+
#398000
0+
#399000
b111 G
b110 A
b110 ;
1+
#400000
0+
#401000
b111 ;
b111 A
b0 G
1+
#402000
0+
#403000
b1 G
b0 A
b0 ;
1+
#404000
0+
#405000
b1 ;
b1 A
b10 G
1+
#406000
0+
#407000
b11 G
b10 A
b10 ;
1+
#408000
0+
#409000
b11 ;
b11 A
b100 G
1+
#410000
0+
#411000
b101 G
b100 A
b100 ;
1+
#412000
0+
#413000
b101 ;
b101 A
b110 G
1+
#414000
0+
#415000
b111 G
b110 A
b110 ;
1+
#416000
0+
#417000
b111 ;
b111 A
b0 G
1+
#418000
0+
#419000
b1 G
b0 A
b0 ;
1+
#420000
0+
#421000
b1 ;
b1 A
b10 G
1+
#422000
0+
#423000
b11 G
b10 A
b10 ;
1+
#424000
0+
#425000
b11 ;
b11 A
b100 G
1+
#426000
0+
#427000
b101 G
b100 A
b100 ;
1+
#428000
0+
#429000
b101 ;
b101 A
b110 G
1+
#430000
0+
#431000
b111 G
b110 A
b110 ;
1+
#432000
0+
#433000
b111 ;
b111 A
b0 G
1+
#434000
0+
#435000
b1 G
b0 A
b0 ;
1+
#436000
0+
#437000
b1 ;
b1 A
b10 G
1+
#438000
0+
#439000
b11 G
b10 A
b10 ;
1+
#440000
0+
#441000
b11 ;
b11 A
b100 G
1+
#442000
0+
#443000
b101 G
b100 A
b100 ;
1+
#444000
0+
#445000
b101 ;
b101 A
b110 G
1+
#446000
0+
#447000
b111 G
b110 A
b110 ;
1+
#448000
0+
#449000
b111 ;
b111 A
b0 G
1+
#450000
0+
#451000
b1 G
b0 A
b0 ;
1+
#452000
0+
#453000
b1 ;
b1 A
b10 G
1+
#454000
0+
#455000
b11 G
b10 A
b10 ;
1+
#456000
0+
#457000
b11 ;
b11 A
b100 G
1+
#458000
0+
#459000
b101 G
b100 A
b100 ;
1+
#460000
0+
#461000
b101 ;
b101 A
b110 G
1+
#462000
0+
#463000
b111 G
b110 A
b110 ;
1+
#464000
0+
#465000
b111 ;
b111 A
b0 G
1+
#466000
0+
#467000
b1 G
b0 A
b0 ;
1+
#468000
0+
#469000
b1 ;
b1 A
b10 G
1+
#470000
0+
#471000
b11 G
b10 A
b10 ;
1+
#472000
0+
#473000
b11 ;
b11 A
b100 G
1+
#474000
0+
#475000
b101 G
b100 A
b100 ;
1+
#476000
0+
#477000
b101 ;
b101 A
b110 G
1+
#478000
0+
#479000
b111 G
b110 A
b110 ;
1+
#480000
0+
#481000
b111 ;
b111 A
b0 G
1+
#482000
0+
#483000
b1 G
b0 A
b0 ;
1+
#484000
0+
#485000
b1 ;
b1 A
b10 G
1+
#486000
0+
#487000
b11 G
b10 A
b10 ;
1+
#488000
0+
#489000
b11 ;
b11 A
b100 G
1+
#490000
0+
#491000
b101 G
b100 A
b100 ;
1+
#492000
0+
#493000
b101 ;
b101 A
b110 G
1+
#494000
0+
#495000
b111 G
b110 A
b110 ;
1+
#496000
0+
#497000
b111 ;
b111 A
b0 G
1+
#498000
0+
#499000
b1 G
b0 A
b0 ;
1+
#500000
0+
#501000
b1 ;
b1 A
b10 G
1+
#502000
0+
#503000
b11 G
b10 A
b10 ;
1+
#504000
0+
#505000
b11 ;
b11 A
b100 G
1+
#506000
0+
#507000
b101 G
b100 A
b100 ;
1+
#508000
0+
#509000
b101 ;
b101 A
b110 G
1+
#510000
0+
#511000
b111 G
b110 A
b110 ;
1+
#512000
0+
#513000
b111 ;
b111 A
b0 G
1+
#514000
0+
#515000
b1 G
b0 A
b0 ;
1+
#516000
0+
#517000
b1 ;
b1 A
b10 G
1+
#518000
0+
#519000
b11 G
b10 A
b10 ;
1+
#520000
0+
#521000
b11 ;
b11 A
b100 G
1+
#522000
0+
#523000
b101 G
b100 A
b100 ;
1+
#524000
0+
#525000
b101 ;
b101 A
b110 G
1+
#526000
0+
#527000
b111 G
b110 A
b110 ;
1+
#528000
0+
#529000
b111 ;
b111 A
b0 G
1+
#530000
0+
#531000
b1 G
b0 A
b0 ;
1+
#532000
0+
#533000
b1 ;
b1 A
b10 G
1+
#534000
0+
#535000
b11 G
b10 A
b10 ;
1+
#536000
0+
#537000
b11 ;
b11 A
b100 G
1+
#538000
0+
#539000
b101 G
b100 A
b100 ;
1+
#540000
0+
#541000
b101 ;
b101 A
b110 G
1+
#542000
0+
#543000
b111 G
b110 A
b110 ;
1+
#544000
0+
#545000
b111 ;
b111 A
b0 G
1+
#546000
0+
#547000
b1 G
b0 A
b0 ;
1+
#548000
0+
#549000
b1 ;
b1 A
b10 G
1+
#550000
0+
#551000
b11 G
b10 A
b10 ;
1+
#552000
0+
#553000
b11 ;
b11 A
b100 G
1+
#554000
0+
#555000
b101 G
b100 A
b100 ;
1+
#556000
0+
#557000
b101 ;
b101 A
b110 G
1+
#558000
0+
#559000
b111 G
b110 A
b110 ;
1+
#560000
0+
#561000
b111 ;
b111 A
b0 G
1+
#562000
0+
#563000
b1 G
b0 A
b0 ;
1+
#564000
0+
#565000
b1 ;
b1 A
b10 G
1+
#566000
0+
#567000
b11 G
b10 A
b10 ;
1+
#568000
0+
#569000
b11 ;
b11 A
b100 G
1+
#570000
0+
#571000
b101 G
b100 A
b100 ;
1+
#572000
0+
#573000
b101 ;
b101 A
b110 G
1+
#574000
0+
#575000
b111 G
b110 A
b110 ;
1+
#576000
0+
#577000
b111 ;
b111 A
b0 G
1+
#578000
0+
#579000
b1 G
b0 A
b0 ;
1+
#580000
0+
#581000
b1 ;
b1 A
b10 G
1+
#582000
0+
#583000
b11 G
b10 A
b10 ;
1+
#584000
0+
#585000
b11 ;
b11 A
b100 G
1+
#586000
0+
#587000
b101 G
b100 A
b100 ;
1+
#588000
0+
#589000
b101 ;
b101 A
b110 G
1+
#590000
0+
#591000
b111 G
b110 A
b110 ;
1+
#592000
0+
#593000
b111 ;
b111 A
b0 G
1+
#594000
0+
#595000
b1 G
b0 A
b0 ;
1+
#596000
0+
#597000
b1 ;
b1 A
b10 G
1+
#598000
0+
#599000
b11 G
b10 A
b10 ;
1+
#600000
0+
#601000
b11 ;
b11 A
b100 G
1+
#602000
0+
#603000
b101 G
b100 A
b100 ;
1+
#604000
0+
#605000
b101 ;
b101 A
b110 G
1+
#606000
0+
#607000
b111 G
b110 A
b110 ;
1+
#608000
0+
#609000
b111 ;
b111 A
b0 G
1+
#610000
0+
#611000
b1 G
b0 A
b0 ;
1+
#612000
0+
#613000
b1 ;
b1 A
b10 G
1+
#614000
0+
#615000
b11 G
b10 A
b10 ;
1+
#616000
0+
#617000
b11 ;
b11 A
b100 G
1+
#618000
0+
#619000
b101 G
b100 A
b100 ;
1+
#620000
0+
#621000
b101 ;
b101 A
b110 G
1+
#622000
0+
#623000
b111 G
b110 A
b110 ;
1+
#624000
0+
#625000
b111 ;
b111 A
b0 G
1+
#626000
0+
#627000
b1 G
b0 A
b0 ;
1+
#628000
0+
#629000
b1 ;
b1 A
b10 G
1+
#630000
0+
#631000
b11 G
b10 A
b10 ;
1+
#632000
0+
#633000
b11 ;
b11 A
b100 G
1+
#634000
0+
#635000
b101 G
b100 A
b100 ;
1+
#636000
0+
#637000
b101 ;
b101 A
b110 G
1+
#638000
0+
#639000
b111 G
b110 A
b110 ;
1+
#640000
0+
#641000
b111 ;
b111 A
b0 G
1+
#642000
0+
#643000
b1 G
b0 A
b0 ;
1+
#644000
0+
#645000
b1 ;
b1 A
b10 G
1+
#646000
0+
#647000
b11 G
b10 A
b10 ;
1+
#648000
0+
#649000
b11 ;
b11 A
b100 G
1+
#650000
0+
#651000
b101 G
b100 A
b100 ;
1+
#652000
0+
#653000
b101 ;
b101 A
b110 G
1+
#654000
0+
#655000
b111 G
b110 A
b110 ;
1+
#656000
0+
#657000
b111 ;
b111 A
b0 G
1+
#658000
0+
#659000
b1 G
b0 A
b0 ;
1+
#660000
0+
#661000
b1 ;
b1 A
b10 G
1+
#662000
0+
#663000
b11 G
b10 A
b10 ;
1+
#664000
0+
#665000
b11 ;
b11 A
b100 G
1+
#666000
0+
#667000
b101 G
b100 A
b100 ;
1+
#668000
0+
#669000
b101 ;
b101 A
b110 G
1+
#670000
0+
#671000
b111 G
b110 A
b110 ;
1+
#672000
0+
#673000
b111 ;
b111 A
b0 G
1+
#674000
0+
#675000
b1 G
b0 A
b0 ;
1+
#676000
0+
#677000
b1 ;
b1 A
b10 G
1+
#678000
0+
#679000
b11 G
b10 A
b10 ;
1+
#680000
0+
#681000
b11 ;
b11 A
b100 G
1+
#682000
0+
#683000
b101 G
b100 A
b100 ;
1+
#684000
0+
#685000
b101 ;
b101 A
b110 G
1+
#686000
0+
#687000
b111 G
b110 A
b110 ;
1+
#688000
0+
#689000
b111 ;
b111 A
b0 G
1+
#690000
0+
#691000
b1 G
b0 A
b0 ;
1+
#692000
0+
#693000
b1 ;
b1 A
b10 G
1+
#694000
0+
#695000
b11 G
b10 A
b10 ;
1+
#696000
0+
#697000
b11 ;
b11 A
b100 G
1+
#698000
0+
#699000
b101 G
b100 A
b100 ;
1+
#700000
0+
#701000
b101 ;
b101 A
b110 G
1+
#702000
0+
#703000
b111 G
b110 A
b110 ;
1+
#704000
0+
#705000
b111 ;
b111 A
b0 G
1+
#706000
0+
#707000
b1 G
b0 A
b0 ;
1+
#708000
0+
#709000
b1 ;
b1 A
b10 G
1+
#710000
0+
#711000
b11 G
b10 A
b10 ;
1+
#712000
0+
#713000
b11 ;
b11 A
b100 G
1+
#714000
0+
#715000
b101 G
b100 A
b100 ;
1+
#716000
0+
#717000
b101 ;
b101 A
b110 G
1+
#718000
0+
#719000
b111 G
b110 A
b110 ;
1+
#720000
0+
#721000
b111 ;
b111 A
b0 G
1+
#722000
0+
#723000
b1 G
b0 A
b0 ;
1+
#724000
0+
#725000
b1 ;
b1 A
b10 G
1+
#726000
0+
#727000
b11 G
b10 A
b10 ;
1+
#728000
0+
#729000
b11 ;
b11 A
b100 G
1+
#730000
0+
#731000
b101 G
b100 A
b100 ;
1+
#732000
0+
#733000
b101 ;
b101 A
b110 G
1+
#734000
0+
#735000
b111 G
b110 A
b110 ;
1+
#736000
0+
#737000
b111 ;
b111 A
b0 G
1+
#738000
0+
#739000
b1 G
b0 A
b0 ;
1+
#740000
0+
#741000
b1 ;
b1 A
b10 G
1+
#742000
0+
#743000
b11 G
b10 A
b10 ;
1+
#744000
0+
#745000
b11 ;
b11 A
b100 G
1+
#746000
0+
#747000
b101 G
b100 A
b100 ;
1+
#748000
0+
#749000
b101 ;
b101 A
b110 G
1+
#750000
0+
#751000
b111 G
b110 A
b110 ;
1+
#752000
0+
